cloudimized/__init__.py
cloudimized/azurecore/__init__.py
cloudimized/azurecore/aksclustersquery.py
cloudimized/azurecore/applicationsecuritygroupsquery.py
cloudimized/azurecore/azurecredential.py
cloudimized/azurecore/azurequery.py
cloudimized/azurecore/networkinterfacesquery.py
cloudimized/azurecore/networksecuritygroupsquery.py
cloudimized/azurecore/resourcegroupsquery.py
cloudimized/azurecore/subscriptionsquery.py
cloudimized/azurecore/virtualnetworksquery.py
cloudimized/azurecore/vnetgatewaysquery.py
cloudimized/core/__init__.py
cloudimized/core/changeprocessor.py
cloudimized/core/core.py
cloudimized/core/jiranotifier.py
cloudimized/core/result.py
cloudimized/core/run.py
cloudimized/core/slacknotifier.py
cloudimized/gcpcore/__init__.py
cloudimized/gcpcore/gcpchangelog.py
cloudimized/gcpcore/gcpexternaltoken.py
cloudimized/gcpcore/gcpquery.py
cloudimized/gcpcore/gcpservicequery.py
cloudimized/gitcore/__init__.py
cloudimized/gitcore/gitchange.py
cloudimized/gitcore/repo.py
cloudimized/tfcore/__init__.py
cloudimized/tfcore/query.py
cloudimized/tfcore/run.py
cloudimized-2.0.3.dist-info/licenses/LICENSE
cloudimized-2.0.3.dist-info/METADATA
cloudimized-2.0.3.dist-info/WHEEL
cloudimized-2.0.3.dist-info/entry_points.txt
cloudimized-2.0.3.dist-info/top_level.txt
cloudimized-2.0.3.dist-info/RECORD
