Metadata-Version: 2.4
Name: cloudimized
Version: 2.0.3
Summary: GCP & Azure configuration scanning tool
Home-page: https://github.com/egnyte/cloudimized
Author: Egnyte and Contributors
Classifier: Programming Language :: Python :: 3.9
Classifier: Programming Language :: Python :: 3.10
Classifier: Development Status :: 5 - Production/Stable
Classifier: Intended Audience :: Information Technology
Classifier: Intended Audience :: System Administrators
Classifier: License :: OSI Approved :: MIT License
Classifier: Operating System :: POSIX :: Linux
Classifier: Operating System :: MacOS
License-File: LICENSE
Requires-Dist: azure-common==1.1.28
Requires-Dist: azure-core==1.32.0
Requires-Dist: azure-identity==1.19.0
Requires-Dist: azure-mgmt-containerservice==34.2.0
Requires-Dist: azure-mgmt-core==1.5.0
Requires-Dist: azure-mgmt-network==28.1.0
Requires-Dist: azure-mgmt-resource==23.2.0
Requires-Dist: azure-mgmt-subscription==3.1.1
Requires-Dist: cachetools==5.5.0
Requires-Dist: certifi==2024.12.14
Requires-Dist: cffi==1.17.1
Requires-Dist: charset-normalizer==3.4.1
Requires-Dist: cryptography==44.0.1
Requires-Dist: defusedxml==0.7.1
Requires-Dist: Deprecated==1.2.15
Requires-Dist: flatdict==4.0.1
Requires-Dist: gitdb==4.0.12
Requires-Dist: GitPython==3.1.44
Requires-Dist: google-api-core==2.24.0
Requires-Dist: google-api-python-client==2.156.0
Requires-Dist: google-auth==2.37.0
Requires-Dist: google-auth-httplib2==0.2.0
Requires-Dist: google-cloud-appengine-logging==1.5.0
Requires-Dist: google-cloud-audit-log==0.3.0
Requires-Dist: google-cloud-core==2.4.1
Requires-Dist: google-cloud-logging==3.11.3
Requires-Dist: googleapis-common-protos==1.66.0
Requires-Dist: grpc-google-iam-v1==0.13.1
Requires-Dist: grpcio==1.68.1
Requires-Dist: grpcio-status==1.68.1
Requires-Dist: httplib2==0.22.0
Requires-Dist: idna==3.10
Requires-Dist: importlib_metadata==8.5.0
Requires-Dist: isodate==0.7.2
Requires-Dist: jira==3.8.0
Requires-Dist: msal==1.31.1
Requires-Dist: msal-extensions==1.2.0
Requires-Dist: msrest==0.7.1
Requires-Dist: oauthlib==3.2.2
Requires-Dist: opentelemetry-api==1.29.0
Requires-Dist: packaging==24.2
Requires-Dist: pillow==11.1.0
Requires-Dist: pip-install==1.3.5
Requires-Dist: portalocker==2.10.1
Requires-Dist: proto-plus==1.25.0
Requires-Dist: protobuf==5.29.5
Requires-Dist: pyasn1==0.6.1
Requires-Dist: pyasn1_modules==0.4.1
Requires-Dist: pycparser==2.22
Requires-Dist: PyJWT==2.10.1
Requires-Dist: pyparsing==3.2.1
Requires-Dist: PyYAML==6.0.2
Requires-Dist: requests==2.32.4
Requires-Dist: requests-oauthlib==2.0.0
Requires-Dist: requests-toolbelt==1.0.0
Requires-Dist: rsa==4.9
Requires-Dist: six==1.17.0
Requires-Dist: slack_sdk==3.34.0
Requires-Dist: smmap==5.0.2
Requires-Dist: terrasnek==0.1.14
Requires-Dist: typing_extensions==4.12.2
Requires-Dist: uritemplate==4.1.1
Requires-Dist: urllib3==2.6.0
Requires-Dist: wrapt==1.17.0
Requires-Dist: zipp==3.21.0
Provides-Extra: test
Requires-Dist: mock; extra == "test"
Requires-Dist: time_machine; extra == "test"
Dynamic: author
Dynamic: classifier
Dynamic: description
Dynamic: description-content-type
Dynamic: home-page
Dynamic: license-file
Dynamic: provides-extra
Dynamic: requires-dist
Dynamic: summary
